dependence/__init__.py
dependence/__main__.py
dependence/_utilities.py
dependence/freeze.py
dependence/py.typed
dependence/update.py
dependence/upgrade.py
dependence-1.2.7.dist-info/METADATA
dependence-1.2.7.dist-info/WHEEL
dependence-1.2.7.dist-info/entry_points.txt
dependence-1.2.7.dist-info/RECORD
