Metadata-Version: 2.4
Name: dependence
Version: 1.2.7
Summary: A dependency management tool for python projects
Project-URL: Documentation, https://dependence.enorganic.org
Project-URL: Repository, https://github.com/enorganic/dependence
Author-email: david@belais.me
License-Expression: MIT
Keywords: dependencies,requirements
Requires-Python: ~=3.10
Requires-Dist: jsonpointer
Requires-Dist: packaging
Requires-Dist: pip
Requires-Dist: setuptools>63
Requires-Dist: tomli-w~=1.2
Requires-Dist: tomli~=2.3
